cleansor/__init__.py
cleansor/__main__.py
cleansor-0.0.4.dist-info/LICENSE
cleansor-0.0.4.dist-info/WHEEL
cleansor-0.0.4.dist-info/METADATA
cleansor-0.0.4.dist-info/RECORD
