Metadata-Version: 2.1
Name: cleansor
Version: 0.0.4
Summary: duplicate file cleansor
Author-email: calcuis <calculatics@gmail.com>
Classifier: License :: OSI Approved :: MIT License
Project-URL: Homepage, https://github.com/calcuis/cleansor
Project-URL: Issues, https://github.com/calcuis/cleansor/issues
